python_md.py
python_md-1.0.2.dist-info/LICENSE
python_md-1.0.2.dist-info/METADATA
python_md-1.0.2.dist-info/WHEEL
python_md-1.0.2.dist-info/top_level.txt
python_md-1.0.2.dist-info/RECORD
