Metadata-Version: 2.1
Name: python-md
Version: 1.0.2
Summary: A simple Markdown writer
Home-page: https://gitlab.com/mdval/python-md
Author: Marina Valverde
Author-email: mdval.eh@gmail.com
License: UNKNOWN
Project-URL: Bug Tracker, https://gitlab.com/mdval/python-md/issues
Keywords: markdown,md,python,python3
Platform: UNKNOWN
Classifier: Programming Language :: Python :: 3
Classifier: License :: OSI Approved :: MIT License
Classifier: Operating System :: OS Independent
Requires-Python: >=3.6
